{
  "announce": "http://bt.aux-cache.dev:9996/announce",
  "created by": "Transmission/3.00 (bb6b5a062e)",
  "creation date": 1716916290,
  "encoding": "UTF-8",
  "info": {
    "files": [
      {
        "length": 793,
        "path": [
          "m68vj0pg2lvrsc23h7lrchv1qzpwpym4.narinfo"
        ]
      },
      {
        "length": 1604,
        "path": [
          "nar",
          "1paq8i52xylbxn9xs609mbqqhirrb8fj4vpgczmgj0701aa6rr5b.nar.xz"
        ]
      }
    ],
    "name": "nix",
    "piece length": 32768,
    "pieces": "XIIYEfmJ3EDUdyaja9RYP4fHfF8=\n",
    "private": 0
  }
}
