{
  "announce": "http://bt.aux-cache.dev:9996/announce",
  "created by": "Transmission/3.00 (bb6b5a062e)",
  "creation date": 1716915814,
  "encoding": "UTF-8",
  "info": {
    "files": [
      {
        "length": 516,
        "path": [
          "j7yk5caljxg94g6kn285hz5ysiyv1bmi.narinfo"
        ]
      },
      {
        "length": 340,
        "path": [
          "nar",
          "17ylkz5b58bg5s970faxsiw72q8k0zyvq4nzb1jwkqvm785ccm9q.nar.xz"
        ]
      }
    ],
    "name": "nix",
    "piece length": 32768,
    "pieces": "iLZU5UGSsJ4QczaNy5QOs/ftCu0=\n",
    "private": 0
  }
}
